temperature_snspds_influx/__init__.py
temperature_snspds_influx/__main__.py
temperature_snspds_influx/config.example.toml
temperature_snspds_influx/config.py
temperature_snspds_influx/ctc.py
temperature_snspds_influx/data.py
temperature_snspds_influx-0.1.0.dist-info/METADATA
temperature_snspds_influx-0.1.0.dist-info/WHEEL
temperature_snspds_influx-0.1.0.dist-info/entry_points.txt
temperature_snspds_influx-0.1.0.dist-info/licenses/LICENSE
temperature_snspds_influx-0.1.0.dist-info/RECORD
