Metadata-Version: 2.4
Name: temperature-snspds-influx
Version: 0.1.0
Summary: temperature-snspds-influx, a tool to publish SNSPDs temperatures (from the CTC100) to an influx database.
License-File: LICENSE
Author: Yoann Piétri
Author-email: Yoann.Pietri@lip6.fr
Requires-Python: >=3.10, <4.0
Classifier: Programming Language :: Python :: 3
Classifier: Programming Language :: Python :: 3.10
Classifier: Programming Language :: Python :: 3.11
Classifier: Programming Language :: Python :: 3.12
Classifier: Programming Language :: Python :: 3.13
Classifier: Programming Language :: Python :: 3.14
Requires-Dist: influxdb3-python (>=0.16.0,<0.17.0)
Requires-Dist: pyserial (>=3.5,<4.0)
